{
  "repositoryDefinition": {
    "type": "object",
    "properties": {
      "mongo_install_path": {
        "type": "string",
        "prettyName": "Mongo Install Path",
        "description": "Path to Mongo binaries"
      },
      "mongo_shell_path": {
        "type": "string",
        "prettyName": "Mongo Shell Path",
        "description": "Path to Mongo Shell"
      },
      "version": {
        "type": "string",
        "prettyName": "Version",
        "description": "MongoDB Version"
      },
      "pretty_name": {
        "type": "string",
        "prettyName": "Pretty Name",
        "description": "Pretty name of this repository"
      }
    },
    "nameField": "pretty_name",
    "identityFields": [
      "mongo_install_path",
      "mongo_shell_path",
      "pretty_name"
    ]
  },
  "sourceConfigDefinition": {
    "type": "object",
    "required": [
      "discovery_type",
      "pretty_name"
    ],
    "ordering": [
      "discovery_type",
      "pretty_name"
    ],
    "additionalProperties": false,
    "properties": {
      "discovery_type": {
        "default": "Manual",
        "type": "string",
        "enum": [
          "Manual",
          "Auto"
        ],
        "prettyName": "discoveryType",
        "description": ""
      },
      "pretty_name": {
        "type": "string",
        "prettyName": "Identity Field",
        "description": "Recommended : Unique dsource name",
        "default": ""
      }
    },
    "nameField": "pretty_name",
    "identityFields": [
      "pretty_name"
    ]
  },
  "virtualSourceDefinition": {
    "type": "object",
    "additionalProperties": false,
    "required": [
      "mount_path",
      "bind_ip",
      "oplog_size",
      "journal_interval",
      "mongo_db_password",
      "make_shards_replicaset"
    ],
    "ordering": [
      "mount_path",
      "bind_ip",
      "start_portpool",
      "oplog_size",
      "journal_interval",
      "mongo_db_password",
      "make_shards_replicaset",
      "additional_nodes",
      "mongos_port",
      "enable_ssl_tls",
      "ssl_tls_params",
      "enable_authentication",
      "user_auth_mode",
      "keyfile_path",
      "cluster_auth_mode",
      "encryption_keyfile",
      "kmip_params",
      "enable_ldap",
      "ldap_params",
      "enable_auditlog",
      "auditlog_params",
      "enable_setparams",
      "setparam_params",
      "client_tls_cert",
      "client_tls_cacert"
    ],
    "properties": {
      "mount_path": {
        "type": "string",
        "prettyName": "Mount Path",
        "description": "",
        "default": ""
      },
      "bind_ip": {
        "type": "string",
        "prettyName": "bindIP String",
        "description": "CSV string of allowed IPs",
        "default": "0.0.0.0",
        "environmentVariable": "MONGO_BIND_IP"
      },
      "oplog_size": {
        "type": "integer",
        "prettyName": "Oplog Size (MB)",
        "description": "",
        "default": 1024,
        "environmentVariable": "MONGO_OPLOG_SIZE"
      },
      "journal_interval": {
        "type": "integer",
        "prettyName": "Journal Commit Interval (ms)",
        "description": "",
        "default": 30,
        "environmentVariable": "MONGO_JOURNAL_FLUSH"
      },
      "mongo_db_password": {
        "type": "string",
        "format": "password",
        "prettyName": "MongoDB Admin/Clusteradmin User Password",
        "description": "",
        "default": "delphix"
      },
      "make_shards_replicaset": {
        "default": false,
        "type": "boolean",
        "prettyName": "Convert each shards to replicaset",
        "description": ""
      },
      "additional_nodes": {
        "items": {
          "ordering": [
            "add_node",
            "environment",
            "environment_user"
          ],
          "required": [
            "add_node",
            "environment",
            "environment_user"
          ],
          "type": "object",
          "properties": {
            "add_node": {
              "prettyName": "add_node",
              "type": "boolean",
              "description": "",
              "default": false
            },
            "environment": {
              "referenceType": "UnixHostEnvironment",
              "prettyName": "Environment",
              "type": "string",
              "description": "",
              "format": "reference"
            },
            "environment_user": {
              "description": "",
              "format": "reference",
              "matches": "environment",
              "referenceType": "EnvironmentUser",
              "prettyName": "Environment User",
              "type": "string"
            }
          }
        },
        "prettyName": "Additional Nodes",
        "type": "array"
      },
      "mongos_port": {
        "type": "integer",
        "prettyName": "Mongos Port Number",
        "description": "",
        "default": 29017
      },
      "start_portpool": {
        "type": "integer",
        "prettyName": "Target Port / Target Port Pool for Mongo Instance(s). Specify only first port for sharded mongo",
        "description": "",
        "default": 29018
      },
      "enable_ssl_tls": {
        "default": false,
        "type": "boolean",
        "prettyName": "Enable SSL/TLS",
        "description": ""
      },
      "ssl_tls_params": {
        "type": "array",
        "prettyName": "SSL/TLS Parameters",
        "description": "",
        "items": {
          "type": "object",
          "required": [
            "property_name",
            "value"
          ],
          "ordering": [
            "property_name",
            "value"
          ],
          "properties": {
            "property_name": {
              "type": "string",
              "prettyName": "Parameter Name [ Enter command line parameter ]",
              "default": "",
              "maxLength": 35,
              "description": "e.g. tlsMode, tlsCAFile, tlsPEMKeyFile, sslAllowConnectionsWithoutCertificates"
            },
            "value": {
              "type": "string",
              "prettyName": "Parameter Value",
              "default": "",
              "maxLength": 100
            }
          }
        },
        "uniqueItems": true
      },
      "enable_authentication": {
        "default": false,
        "type": "boolean",
        "prettyName": "Enable Authentication",
        "description": ""
      },
      "user_auth_mode": {
        "type": "string",
        "prettyName": "User Auth Mode",
        "description": "",
        "enum": [
          "None",
          "SCRAM",
          "x509",
          "ldap"
        ],
        "default": "None"
      },
      "keyfile_path": {
        "type": "string",
        "prettyName": "KeyAuth keyfile name (Full Path)",
        "description": "KeyAuth keyfile name accessible on target host(s), owned by delphix o/s user with 600 permissions",
        "default": ""
      },
      "cluster_auth_mode": {
        "type": "string",
        "prettyName": "Cluster Auth Mode",
        "description": "",
        "enum": [
          "None",
          "keyFile",
          "x509",
          "sendKeyFile",
          "sendX509"
        ],
        "default": "None"
      },
      "encryption_keyfile": {
        "type": "string",
        "prettyName": "Local Encryption KeyFile",
        "description": "",
        "default": ""
      },
      "kmip_params": {
        "type": "array",
        "prettyName": "KMIP Parameters",
        "description": "",
        "items": {
          "type": "object",
          "required": [
            "property_name",
            "value"
          ],
          "ordering": [
            "property_name",
            "value"
          ],
          "properties": {
            "property_name": {
              "type": "string",
              "prettyName": "Parameter Name [ Enter command line parameter ]",
              "default": "",
              "maxLength": 35,
              "description": "e.g. kmipClientCertificateFile, kmipPort, kmipServerCAFile, kmipServerName"
            },
            "value": {
              "type": "string",
              "prettyName": "Parameter Value",
              "default": "",
              "maxLength": 100
            }
          }
        }
      },
      "enable_ldap": {
        "default": false,
        "type": "boolean",
        "prettyName": "Enable LDAP",
        "description": ""
      },
      "ldap_params": {
        "type": "array",
        "prettyName": "LDAP Parameters",
        "description": "",
        "items": {
          "type": "object",
          "required": [
            "property_name",
            "value"
          ],
          "ordering": [
            "property_name",
            "value"
          ],
          "properties": {
            "property_name": {
              "type": "string",
              "prettyName": "Parameter Name [ Enter command line parameter ]",
              "default": "",
              "maxLength": 35,
              "description": "e.g. ldapBindMethod, ldapQueryPassword, ldapServers, ldapTimeoutMS"
            },
            "value": {
              "type": "string",
              "prettyName": "Parameter Value",
              "default": "",
              "maxLength": 100
            }
          }
        }
      },
      "enable_auditlog": {
        "default": false,
        "type": "boolean",
        "prettyName": "Enable Auditlog",
        "description": ""
      },
      "auditlog_params": {
        "type": "array",
        "prettyName": "Auditlog Parameters",
        "description": "",
        "items": {
          "type": "object",
          "required": [
            "property_name",
            "value"
          ],
          "ordering": [
            "property_name",
            "value"
          ],
          "properties": {
            "property_name": {
              "type": "string",
              "prettyName": "Parameter Name [ Enter command line parameter ]",
              "default": "",
              "maxLength": 35,
              "description": "e.g. auditDestination, auditFilter"
            },
            "value": {
              "type": "string",
              "prettyName": "Parameter Value",
              "default": "",
              "maxLength": 100
            }
          }
        }
      },
      "enable_setparams": {
        "default": false,
        "type": "boolean",
        "prettyName": "Enable SetParams",
        "description": ""
      },
      "setparam_params": {
        "type": "array",
        "prettyName": "Set Parameter",
        "description": "",
        "items": {
          "type": "object",
          "required": [
            "property_name",
            "value"
          ],
          "ordering": [
            "property_name",
            "value"
          ],
          "properties": {
            "property_name": {
              "type": "string",
              "prettyName": "Parameter Name [ Enter command line parameter ]",
              "default": "",
              "maxLength": 35,
              "description": "e.g. authenticationMechanisms, opensslCipherConfig"
            },
            "value": {
              "type": "string",
              "prettyName": "Parameter Value",
              "default": "",
              "maxLength": 100
            }
          }
        }
      },
      "client_tls_cert": {
        "type": "string",
        "prettyName": "Client Certificate for Mongos session on Primary Node",
        "description": "owned by delphix o/s user with 600 permissions",
        "default": ""
      },
      "client_tls_cacert": {
        "type": "string",
        "prettyName": "Client CA Certificate for Mongos session on Primary Node",
        "description": "owned by delphix o/s user with 600 permissions",
        "default": ""
      }
    }
  },
  "linkedSourceDefinition": {
    "type": "object",
    "additionalProperties": false,
    "required": [
      "d_source_type",
      "mongo_host",
      "start_portpool",
      "bind_ip",
      "oplog_size",
      "journal_interval",
      "storage_engine",
      "mount_path"
    ],
    "ordering": [
      "d_source_type",
      "src_mongo_host_conn",
      "src_db_user",
      "src_db_password",
      "enable_logsync",
      "mongo_host",
      "start_portpool",
      "mongos_port",
      "bind_ip",
      "oplog_size",
      "journal_interval",
      "storage_engine",
      "mount_path",
      "backup_metadata_file",
      "mongo_db_user",
      "mongo_db_password",
      "source_sharded",
      "config_backupfile",
      "shard_backupfiles",
      "enable_ssl_tls",
      "ssl_tls_params",
      "enable_authentication",
      "user_auth_mode",
      "keyfile_path",
      "cluster_auth_mode",
      "source_encrypted",
      "encryption_method",
      "encryption_keyfile",
      "kmip_params",
      "enable_ldap",
      "ldap_params",
      "enable_auditlog",
      "auditlog_params",
      "enable_setparams",
      "setparam_params",
      "client_tls_cert",
      "client_tls_cacert"
    ],
    "properties": {
      "d_source_type": {
        "type": "string",
        "prettyName": "dSource Type",
        "description": "",
        "enum": [
          "shardedsource",
          "nonshardedsource",
          "offlinemongodump",
          "onlinemongodump",
          "extendedcluster",
          "seed"
        ],
        "default": "shardedsource"
      },
      "mongo_host": {
        "type": "string",
        "prettyName": "Staging MongoDB Host",
        "description": "",
        "default": ""
      },
      "src_mongo_host_conn": {
        "type": "string",
        "prettyName": "Source MongoDB Host Connect String",
        "description": "host:port | replicasetName/host1:port,host2:port,host3:port  [ --ssl ] | [ --tls ]",
        "default": ""
      },
      "src_db_user": {
        "type": "string",
        "prettyName": "MongoDB Source Database User",
        "description": "",
        "default": ""
      },
      "src_db_password": {
        "type": "string",
        "format": "password",
        "prettyName": "MongoDB Password",
        "description": "",
        "default": ""
      },
      "enable_logsync": {
        "default": false,
        "type": "boolean",
        "prettyName": "Enable logsync for mongodumponline of replicaset",
        "description": ""
      },
      "src_replicaset_name": {
        "type": "string",
        "prettyName": "Replicaset Name",
        "description": "",
        "default": ""
      },
      "bind_ip": {
        "type": "string",
        "prettyName": "bindIP String",
        "description": "CSV string of allowed IPs",
        "default": "0.0.0.0",
        "environmentVariable": "MONGO_BIND_IP",
        "condition": "linkedSourceDefinition.d_source_type=='shardedsource'"
      },
      "storage_engine": {
        "type": "string",
        "prettyName": "Storage Engine",
        "description": "",
        "enum": [
          "mmapv1",
          "wiredTiger"
        ],
        "default": "wiredTiger",
        "environmentVariable": "MONGO_STORAGE_ENGINE"
      },
      "oplog_size": {
        "type": "integer",
        "prettyName": "Oplog Size (MB)",
        "description": "",
        "default": 1024,
        "environmentVariable": "MONGO_OPLOG_SIZE"
      },
      "journal_interval": {
        "type": "integer",
        "prettyName": "Journal Commit Interval (ms)",
        "description": "",
        "default": 30,
        "environmentVariable": "MONGO_JOURNAL_FLUSH"
      },
      "make_shards_replicaset": {
        "default": false,
        "type": "boolean",
        "prettyName": "Convert each shards to replicaset",
        "description": ""
      },
      "mount_path": {
        "type": "string",
        "prettyName": "Mount Path",
        "description": "",
        "default": ""
      },
      "backup_metadata_file": {
        "type": "string",
        "prettyName": "Backup Metadata File Name (Backup datetime)",
        "description": "Content - MMDDYYYY_HH24MISS",
        "default": ""
      },
      "source_sharded": {
        "default": true,
        "type": "boolean",
        "prettyName": "Source Sharded Cluster",
        "description": ""
      },
      "config_backupfile": {
        "type": "string",
        "prettyName": "Config Server Backup File (sharded mongo) / replicaset backup file (nonsharded mongo) / Backup directory for Mongodump",
        "description": "for mongodump use backup cmd ( mongodump --oplog --gzip -o )",
        "default": ""
      },
      "shard_backupfiles": {
        "type": "array",
        "prettyName": "Shard Backup Files",
        "description": "",
        "items": {
          "type": "object",
          "required": [
            "backupfile"
          ],
          "ordering": [
            "backupfile"
          ],
          "properties": {
            "backupfile": {
              "type": "string",
              "prettyName": "Backup File",
              "default": "",
              "maxLength": 150
            }
          }
        }
      },
      "enable_ssl_tls": {
        "default": false,
        "type": "boolean",
        "prettyName": "Enable SSL/TLS",
        "description": ""
      },
      "ssl_tls_params": {
        "type": "array",
        "prettyName": "SSL/TLS Parameters",
        "description": "",
        "items": {
          "type": "object",
          "required": [
            "property_name",
            "value"
          ],
          "ordering": [
            "property_name",
            "value"
          ],
          "properties": {
            "property_name": {
              "type": "string",
              "prettyName": "Parameter Name [ Enter command line parameter ]",
              "default": "",
              "maxLength": 40,
              "description": "e.g. tlsMode, tlsCAFile, tlsPEMKeyFile, sslAllowConnectionsWithoutCertificates"
            },
            "value": {
              "type": "string",
              "prettyName": "Parameter Value",
              "default": "",
              "maxLength": 100
            }
          }
        },
        "uniqueItems": true
      },
      "enable_authentication": {
        "default": false,
        "type": "boolean",
        "prettyName": "Enable Authentication",
        "description": ""
      },
      "user_auth_mode": {
        "type": "string",
        "prettyName": "User Auth Mode",
        "description": "",
        "enum": [
          "None",
          "SCRAM",
          "x509",
          "ldap"
        ],
        "default": "SCRAM"
      },
      "keyfile_path": {
        "type": "string",
        "prettyName": "KeyAuth keyfile name (Full Path)",
        "description": "KeyAuth keyfile name accessible on staging host, owned by delphix o/s user with 600 permissions",
        "default": ""
      },
      "cluster_auth_mode": {
        "type": "string",
        "prettyName": "Cluster Auth Mode",
        "description": "",
        "enum": [
          "None",
          "keyFile",
          "x509",
          "sendKeyFile",
          "sendX509"
        ],
        "default": "None"
      },
      "source_encrypted": {
        "default": false,
        "type": "boolean",
        "prettyName": "Source is Encrypted",
        "description": ""
      },
      "encryption_method": {
        "type": "string",
        "prettyName": "Source Encryption Method",
        "description": "",
        "enum": [
          "KeyFile",
          "KMIP"
        ],
        "default": "KeyFile"
      },
      "encryption_keyfile": {
        "type": "string",
        "prettyName": "Local Encryption KeyFile",
        "description": "",
        "default": ""
      },
      "kmip_params": {
        "type": "array",
        "prettyName": "KMIP Parameters",
        "description": "",
        "items": {
          "type": "object",
          "required": [
            "property_name",
            "value"
          ],
          "ordering": [
            "property_name",
            "value"
          ],
          "properties": {
            "property_name": {
              "type": "string",
              "prettyName": "Parameter Name [ Enter command line parameter ]",
              "default": "",
              "maxLength": 40,
              "description": "e.g. kmipClientCertificateFile, kmipPort, kmipServerCAFile, kmipServerName"
            },
            "value": {
              "type": "string",
              "prettyName": "Parameter Value",
              "default": "",
              "maxLength": 100
            }
          }
        }
      },
      "enable_ldap": {
        "default": false,
        "type": "boolean",
        "prettyName": "Enable LDAP",
        "description": ""
      },
      "ldap_params": {
        "type": "array",
        "prettyName": "LDAP Parameters",
        "description": "",
        "items": {
          "type": "object",
          "required": [
            "property_name",
            "value"
          ],
          "ordering": [
            "property_name",
            "value"
          ],
          "properties": {
            "property_name": {
              "type": "string",
              "prettyName": "Parameter Name [ Enter command line parameter ]",
              "default": "",
              "maxLength": 40,
              "description": "e.g. ldapBindMethod, ldapQueryPassword, ldapServers, ldapTimeoutMS"
            },
            "value": {
              "type": "string",
              "prettyName": "Parameter Value",
              "default": "",
              "maxLength": 100
            }
          }
        }
      },
      "enable_auditlog": {
        "default": false,
        "type": "boolean",
        "prettyName": "Enable Auditlog",
        "description": ""
      },
      "auditlog_params": {
        "type": "array",
        "prettyName": "Auditlog Parameters",
        "description": "",
        "items": {
          "type": "object",
          "required": [
            "property_name",
            "value"
          ],
          "ordering": [
            "property_name",
            "value"
          ],
          "properties": {
            "property_name": {
              "type": "string",
              "prettyName": "Parameter Name [ Enter command line parameter ]",
              "default": "",
              "maxLength": 40,
              "description": "e.g. auditDestination, auditFilter"
            },
            "value": {
              "type": "string",
              "prettyName": "Parameter Value",
              "default": "",
              "maxLength": 100
            }
          }
        }
      },
      "enable_setparams": {
        "default": false,
        "type": "boolean",
        "prettyName": "Enable SetParams",
        "description": ""
      },
      "setparam_params": {
        "type": "array",
        "prettyName": "Set Parameter",
        "description": "",
        "items": {
          "type": "object",
          "required": [
            "property_name",
            "value"
          ],
          "ordering": [
            "property_name",
            "value"
          ],
          "properties": {
            "property_name": {
              "type": "string",
              "prettyName": "Parameter Name [ Enter command line parameter ]",
              "default": "",
              "maxLength": 40,
              "description": "e.g. authenticationMechanisms, opensslCipherConfig"
            },
            "value": {
              "type": "string",
              "prettyName": "Parameter Value",
              "default": "",
              "maxLength": 100
            }
          }
        }
      },
      "mongos_port": {
        "type": "integer",
        "prettyName": "Mongos Port Number (ONLY for sharded mongo)",
        "description": "",
        "default": 28017
      },
      "start_portpool": {
        "type": "integer",
        "prettyName": "Staging Port / Staging Port Pool for Mongo Instance(s). Specify only first port for sharded mongo",
        "description": "",
        "default": 28000
      },
      "mongo_db_user": {
        "type": "string",
        "prettyName": "Mongo Admin User",
        "description": "",
        "default": ""
      },
      "mongo_db_password": {
        "type": "string",
        "format": "password",
        "prettyName": "MongoDB Password",
        "description": "",
        "default": ""
      },
      "client_tls_cert": {
        "type": "string",
        "prettyName": "Client Certificate for Mongos / Mongo session on Primary Node",
        "description": "owned by delphix o/s user with 600 permissions",
        "default": ""
      },
      "client_tls_cacert": {
        "type": "string",
        "prettyName": "Client CA Certificate for Mongos / Mongo session on Primary Node",
        "description": "owned by delphix o/s user with 600 permissions",
        "default": ""
      }
    }
  },
  "snapshotDefinition": {
    "type": "object",
    "additionalProperties": false,
    "properties": {
      "toolkit_version": {
        "type": "string"
      },
      "timestamp": {
        "type": "string"
      },
      "architecture": {
        "type": "string"
      },
      "os_type": {
        "type": "string"
      },
      "os_version": {
        "type": "string"
      },
      "mongo_version": {
        "type": "string"
      },
      "delphix_mount": {
        "type": "string"
      },
      "storage_engine": {
        "type": "string"
      },
      "user_auth_auth": {
        "type": "string"
      },
      "keyfile_path": {
        "type": "string"
      },
      "replica_set": {
        "type": "string"
      },
      "journal_interval": {
        "type": "integer"
      },
      "oplog_size": {
        "type": "integer"
      },
      "d_source_type": {
        "type": "string"
      },
      "append_db_path": {
        "type": "string"
      },
      "mongo_db_user": {
        "type": "string"
      },
      "mongo_db_password": {
        "type": "string"
      },
      "source_sharded": {
        "type": "boolean"
      },
      "shard_count": {
        "type": "integer"
      },
      "source_encrypted": {
        "type": "boolean"
      },
      "cluster_auth_mode": {
        "type": "string"
      },
      "encryption_method": {
        "type": "string"
      },
      "encryption_keyfile": {
        "type": "string"
      },
      "kmip_params": {
        "type": "array"
      }
    }
  }
}
